{
    "swagger": "2.0",
    "info": {
        "description": "Ini adalah API server untuk aplikasi E-Meeting.",
        "title": "E-Meeting API",
        "contact": {},
        "version": "1.0"
    },
    "host": "localhost:8080",
    "paths": {
        "/register": {
            "post": {
                "description": "Register user baru",
                "consumes": [
                    "application/json"
                ],
                "produces": [
                    "application/json"
                ],
                "tags": [
                    "Register"
                ],
                "summary": "Register user baru",
                "parameters": [
                    {
                        "description": "Register Request",
                        "name": "request",
                        "in": "body",
                        "required": true,
                        "schema": {
                            "$ref": "#/definitions/handler.RegisterRequest"
                        }
                    }
                ],
                "responses": {
                    "200": {
                        "description": "Register Success",
                        "schema": {
                            "type": "object",
                            "additionalProperties": true
                        }
                    },
                    "400": {
                        "description": "Bad Request",
                        "schema": {
                            "type": "object",
                            "additionalProperties": true
                        }
                    },
                    "500": {
                        "description": "Internal Server Error",
                        "schema": {
                            "type": "object",
                            "additionalProperties": true
                        }
                    }
                }
            }
        },
        "/snacks": {
            "get": {
                "description": "Mengambil seluruh daftar snack yang tersedia",
                "consumes": [
                    "application/json"
                ],
                "produces": [
                    "application/json"
                ],
                "tags": [
                    "Snacks"
                ],
                "summary": "Mendapatkan semua data snack",
                "responses": {
                    "200": {
                        "description": "OK",
                        "schema": {
                            "type": "array",
                            "items": {
                                "$ref": "#/definitions/model.Snack"
                            }
                        }
                    }
                }
            }
        }
    },
    "definitions": {
        "handler.RegisterRequest": {
            "type": "object",
            "properties": {
                "confirmPassword": {
                    "type": "string"
                },
                "email": {
                    "type": "string"
                },
                "password": {
                    "type": "string"
                },
                "username": {
                    "type": "string"
                }
            }
        },
        "model.Snack": {
            "type": "object",
            "properties": {
                "category": {
                    "type": "string"
                },
                "id": {
                    "type": "integer"
                },
                "name": {
                    "type": "string"
                },
                "price": {
                    "type": "number"
                }
            }
        }
    }
}